bre/__init__.py
bre/actions.py
bre/core.py
bre/datatypes.py
bre/i18n.py
bre/operators.py
bre/processor.py
bre/locales/messages.pot
bre/locales/de/LC_MESSAGES/messages.mo
bre/locales/de/LC_MESSAGES/messages.po
bre/locales/en/LC_MESSAGES/messages.mo
bre/locales/en/LC_MESSAGES/messages.po
bre/locales/nl/LC_MESSAGES/messages.mo
bre/locales/nl/LC_MESSAGES/messages.po
tests/__init__.py
tests/fields.py
tests/test_actions.py
tests/test_core.py
tests/test_custom_fields.py
tests/test_customers.py
tests/test_datatype.py
tests/test_extension.py
tests/test_extractors.py
tests/test_i18n.py
tests/test_operators.py
tests/test_processor.py
tests/utils.py
bre_next-0.22.dist-info/METADATA
bre_next-0.22.dist-info/WHEEL
bre_next-0.22.dist-info/top_level.txt
bre_next-0.22.dist-info/RECORD
